{
  "type": "ui-component",
  "title": "Image",
  "icon": "Image",
  "componentType": "Element",
  "description": "A plain old text field",
  "width": 160,
  "height": 35,
  "properties": {
    "source": {
      "type": "string",
      "title": "Image URL",
      "description": "The value to display",
      "default": "Lorem Ipsum"
    },
    "style": {
      "type": "object",
      "title": "Component Styling",
      "description": "The style for the component",
      "properties": {
        "height": {
          "title": "Height",
          "type": "number",
          "default": 35
        },
        "width": {
          "title": "Width",
          "type": "number",
          "default": 175
        }
      }
    },
    "onPress": {
      "title": "onPress",
      "type": "function",
      "arguments": [],
      "returnType": "null"
    }
  }
}
